featureflow/__init__.py
featureflow/condition.py
featureflow/evaluate.py
featureflow/event.py
featureflow/events.py
featureflow/feature.py
featureflow/feature_registration.py
featureflow/featureflow.py
featureflow/polling_client.py
featureflow/rule.py
featureflow/user.py
test/__init__.py
test/test_client.py
test/test_condition.py
test/test_helpers.py
featureflow_sdk-0.1.1.dist-info/LICENSE
featureflow_sdk-0.1.1.dist-info/METADATA
featureflow_sdk-0.1.1.dist-info/WHEEL
featureflow_sdk-0.1.1.dist-info/top_level.txt
featureflow_sdk-0.1.1.dist-info/RECORD
