Metadata-Version: 2.1
Name: featureflow-sdk
Version: 0.1.1
Summary: Python 3 SDK for the featureflow feature management platform
Home-page: https://github.com/featureflow/featureflow-python-sdk
Author: Featureflow
Author-email: featureflow@featureflow.io
License: UNKNOWN
Platform: UNKNOWN
Classifier: Programming Language :: Python :: 3
Classifier: Operating System :: OS Independent
Requires-Python: >=3.6
Requires-Dist: requests
Requires-Dist: Faker
